qchat/__init__.py
qchat/command.py
qchat/main.py
qchat/main_window.py
qchat-0.1.0.dist-info/licenses/LICENSE
qchat-0.1.0.dist-info/METADATA
qchat-0.1.0.dist-info/WHEEL
qchat-0.1.0.dist-info/top_level.txt
qchat-0.1.0.dist-info/RECORD
