Metadata-Version: 2.4
Name: qchat
Version: 0.1.0
Summary: QT6-based Chat UI DevKit with command decorators
Author: Junfeng Geng
License: MIT
Project-URL: Homepage, https://github.com/junfenggeng/qchat
Project-URL: Documentation, https://github.com/junfenggeng/qchat#readme
Project-URL: Issues, https://github.com/junfenggeng/qchat/issues
Project-URL: Source, https://github.com/junfenggeng/qchat
Classifier: License :: OSI Approved :: MIT License
Classifier: Programming Language :: Python :: 3
Classifier: Programming Language :: Python :: 3.8
Classifier: Programming Language :: Python :: 3.9
Classifier: Programming Language :: Python :: 3.10
Classifier: Programming Language :: Python :: 3.11
Classifier: Programming Language :: Python :: 3.12
Requires-Python: >=3.8
License-File: LICENSE
Requires-Dist: PySide6>=6.0.0
Provides-Extra: dev
Requires-Dist: black; extra == "dev"
Requires-Dist: flake8; extra == "dev"
Requires-Dist: mypy; extra == "dev"
Requires-Dist: pytest; extra == "dev"
Dynamic: license-file
